video_format_converter_mcp/__init__.py
video_format_converter_mcp/main.py
video_format_converter_mcp-0.2.9.dist-info/METADATA
video_format_converter_mcp-0.2.9.dist-info/WHEEL
video_format_converter_mcp-0.2.9.dist-info/entry_points.txt
video_format_converter_mcp-0.2.9.dist-info/RECORD
