Metadata-Version: 2.4
Name: video-format-converter-mcp
Version: 0.2.9
Summary: MCP server for video format conversion and property adjustment using FFmpeg
Author-email: Your Name <your.email@example.com>
License: MIT
Keywords: codec,container,conversion,ffmpeg,format,mcp,video
Classifier: Development Status :: 4 - Beta
Classifier: Intended Audience :: Developers
Classifier: License :: OSI Approved :: MIT License
Classifier: Programming Language :: Python :: 3
Classifier: Programming Language :: Python :: 3.12
Classifier: Topic :: Multimedia :: Video
Classifier: Topic :: Multimedia :: Video :: Conversion
Classifier: Topic :: Software Development :: Libraries :: Python Modules
Requires-Python: >=3.12
Requires-Dist: ffmpeg-python>=0.2.0
Requires-Dist: mcp[cli]>=1.9.0
